esridump/__init__.py
esridump/cli.py
esridump/dumper.py
esridump/errors.py
esridump/esri2geojson.py
esridump-1.13.0.dist-info/LICENSE
esridump-1.13.0.dist-info/METADATA
esridump-1.13.0.dist-info/WHEEL
esridump-1.13.0.dist-info/entry_points.txt
esridump-1.13.0.dist-info/top_level.txt
esridump-1.13.0.dist-info/RECORD
