Metadata-Version: 2.1
Name: esridump
Version: 1.13.0
Summary: Dump geodata from ESRI endpoints to GeoJSON
Home-page: https://github.com/openaddresses/pyesridump
Author: Ian Dees
Author-email: ian.dees@gmail.com
License: MIT
License-File: LICENSE
Requires-Dist: requests
Requires-Dist: six
